{"nodes": [{"id": "badge", "label": "badge.tsx", "file_type": "code", "source_file": "packages/ui/src/badge.tsx", "source_location": "L1"}, {"id": "badge_badge", "label": "Badge()", "file_type": "code", "source_file": "packages/ui/src/badge.tsx", "source_location": "L22"}], "edges": [{"source": "badge", "target": "react", "relation": "imports_from", "confidence": "EXTRACTED", "source_file": "packages/ui/src/badge.tsx", "source_location": "L1", "weight": 1.0}, {"source": "badge", "target": "utils_js", "relation": "imports_from", "confidence": "EXTRACTED", "source_file": "packages/ui/src/badge.tsx", "source_location": "L2", "weight": 1.0}, {"source": "badge", "target": "badge_badge", "relation": "contains", "confidence": "EXTRACTED", "source_file": "packages/ui/src/badge.tsx", "source_location": "L22", "weight": 1.0}]}