{"nodes": [{"id": "template_card", "label": "template-card.tsx", "file_type": "code", "source_file": "apps/web/src/components/briefs/templates/template-card.tsx", "source_location": "L1"}, {"id": "template_card_templatecard", "label": "TemplateCard()", "file_type": "code", "source_file": "apps/web/src/components/briefs/templates/template-card.tsx", "source_location": "L11"}], "edges": [{"source": "template_card", "target": "link", "relation": "imports_from", "confidence": "EXTRACTED", "source_file": "apps/web/src/components/briefs/templates/template-card.tsx", "source_location": "L1", "weight": 1.0}, {"source": "template_card", "target": "lucide_react", "relation": "imports_from", "confidence": "EXTRACTED", "source_file": "apps/web/src/components/briefs/templates/template-card.tsx", "source_location": "L2", "weight": 1.0}, {"source": "template_card", "target": "ui", "relation": "imports_from", "confidence": "EXTRACTED", "source_file": "apps/web/src/components/briefs/templates/template-card.tsx", "source_location": "L3", "weight": 1.0}, {"source": "template_card", "target": "status_badge", "relation": "imports_from", "confidence": "EXTRACTED", "source_file": "apps/web/src/components/briefs/templates/template-card.tsx", "source_location": "L4", "weight": 1.0}, {"source": "template_card", "target": "briefs", "relation": "imports_from", "confidence": "EXTRACTED", "source_file": "apps/web/src/components/briefs/templates/template-card.tsx", "source_location": "L5", "weight": 1.0}, {"source": "template_card", "target": "template_card_templatecard", "relation": "contains", "confidence": "EXTRACTED", "source_file": "apps/web/src/components/briefs/templates/template-card.tsx", "source_location": "L11", "weight": 1.0}]}