{"nodes": [{"id": "phaseprogress", "label": "PhaseProgress.tsx", "file_type": "code", "source_file": "apps/web/src/components/onboarding/PhaseProgress.tsx", "source_location": "L1"}], "edges": [{"source": "phaseprogress", "target": "react", "relation": "imports_from", "confidence": "EXTRACTED", "source_file": "apps/web/src/components/onboarding/PhaseProgress.tsx", "source_location": "L3", "weight": 1.0}, {"source": "phaseprogress", "target": "gsap_config", "relation": "imports_from", "confidence": "EXTRACTED", "source_file": "apps/web/src/components/onboarding/PhaseProgress.tsx", "source_location": "L4", "weight": 1.0}, {"source": "phaseprogress", "target": "reducedmotionprovider", "relation": "imports_from", "confidence": "EXTRACTED", "source_file": "apps/web/src/components/onboarding/PhaseProgress.tsx", "source_location": "L5", "weight": 1.0}]}