{"nodes": [{"id": "onboardingchecklist", "label": "OnboardingChecklist.tsx", "file_type": "code", "source_file": "apps/web/src/components/shared/OnboardingChecklist.tsx", "source_location": "L1"}, {"id": "onboardingchecklist_fireconfetti", "label": "fireConfetti()", "file_type": "code", "source_file": "apps/web/src/components/shared/OnboardingChecklist.tsx", "source_location": "L42"}], "edges": [{"source": "onboardingchecklist", "target": "react", "relation": "imports_from", "confidence": "EXTRACTED", "source_file": "apps/web/src/components/shared/OnboardingChecklist.tsx", "source_location": "L3", "weight": 1.0}, {"source": "onboardingchecklist", "target": "framer_motion", "relation": "imports_from", "confidence": "EXTRACTED", "source_file": "apps/web/src/components/shared/OnboardingChecklist.tsx", "source_location": "L4", "weight": 1.0}, {"source": "onboardingchecklist", "target": "lucide_react", "relation": "imports_from", "confidence": "EXTRACTED", "source_file": "apps/web/src/components/shared/OnboardingChecklist.tsx", "source_location": "L5", "weight": 1.0}, {"source": "onboardingchecklist", "target": "link", "relation": "imports_from", "confidence": "EXTRACTED", "source_file": "apps/web/src/components/shared/OnboardingChecklist.tsx", "source_location": "L16", "weight": 1.0}, {"source": "onboardingchecklist", "target": "ui", "relation": "imports_from", "confidence": "EXTRACTED", "source_file": "apps/web/src/components/shared/OnboardingChecklist.tsx", "source_location": "L17", "weight": 1.0}, {"source": "onboardingchecklist", "target": "useonboarding", "relation": "imports_from", "confidence": "EXTRACTED", "source_file": "apps/web/src/components/shared/OnboardingChecklist.tsx", "source_location": "L18", "weight": 1.0}, {"source": "onboardingchecklist", "target": "ui_store", "relation": "imports_from", "confidence": "EXTRACTED", "source_file": "apps/web/src/components/shared/OnboardingChecklist.tsx", "source_location": "L26", "weight": 1.0}, {"source": "onboardingchecklist", "target": "onboardingchecklist_fireconfetti", "relation": "contains", "confidence": "EXTRACTED", "source_file": "apps/web/src/components/shared/OnboardingChecklist.tsx", "source_location": "L42", "weight": 1.0}]}